SPD/__init__.py
SPD/new_lj_thellier_gui_spd.py
SPD/run_tests.py
SPD/spd.py
SPD/test_instance.py
SPD/lib/__init__.py
SPD/lib/leastsq_jacobian.py
SPD/lib/lib_IZZI_MD.py
SPD/lib/lib_additivity_check_statistics.py
SPD/lib/lib_arai_plot_statistics.py
SPD/lib/lib_curvature.py
SPD/lib/lib_directional_statistics.py
SPD/lib/lib_leastsquares.py
SPD/lib/lib_ptrm_statistics.py
SPD/lib/lib_tail_check_statistics.py
SPD/lib/new_lib_curvature.py
SPD/tests/__init__.py
SPD/tests/known_values.py
SPD/tests/test_additivity_check_statistics.py
SPD/tests/test_all.py
SPD/tests/test_arai_plot_statistics.py
SPD/tests/test_curvature.py
SPD/tests/test_directional_statistics.py
SPD/tests/test_ptrm_statistics.py
SPD/tests/test_tail_check_statistics.py
dialogs/ErMagicBuilder.py
dialogs/__init__.py
dialogs/demag_dialogs.py
dialogs/demag_interpretation_editor.py
dialogs/drop_down_menus3.py
dialogs/grid_frame3.py
dialogs/magic_grid2.py
dialogs/magic_grid3.py
dialogs/pmag_er_magic_dialogs.py
dialogs/pmag_gui_dialogs.py
dialogs/pmag_gui_menu3.py
dialogs/pmag_menu_dialogs.py
dialogs/pmag_widgets.py
dialogs/thellier_consistency_test.py
dialogs/thellier_gui_dialogs.py
dialogs/thellier_gui_lib.py
dialogs/thellier_interpreter.py
dialogs/help_files/ErMagicAgeHelp.html
dialogs/help_files/ErMagicBuilderHelp.html
dialogs/help_files/ErMagicHeadersHelp.html
dialogs/help_files/ErMagicLocationHelp.html
dialogs/help_files/ErMagicSampleHelp.html
dialogs/help_files/ErMagicSampleHelp1.html
dialogs/help_files/ErMagicSiteHelp.html
dialogs/help_files/ErMagicSpecimenHelp.html
dialogs/help_files/magic_gui.html
help_files/__init__.py
help_files/demag_gui_help.py
help_files/demag_interpretation_editor_help.py
locator/__init__.py
locator/resource.py
pmagpy/mapping/__init__.py
pmagpy/mapping/map_magic.py
pmagpy/mapping/maps.py
pmagpy/test/__init__.py
pmagpy/test/test_fisher_sample.py
pmagpy/test/test_igrf.py
pmagpy/test/test_rotations.py
pmagpy_cli-4.3.8.data/scripts/ani_depthplot_anaconda
pmagpy_cli-4.3.8.dist-info/METADATA
pmagpy_cli-4.3.8.dist-info/WHEEL
pmagpy_cli-4.3.8.dist-info/entry_points.txt
pmagpy_cli-4.3.8.dist-info/top_level.txt
pmagpy_cli-4.3.8.dist-info/RECORD
