Metadata-Version: 2.1
Name: pmagpy-cli
Version: 4.3.8
Summary: Analysis tools for paleo/rock magnetic data
Home-page: https://github.com/PmagPy/PmagPy
Author: PmagPy team
Author-email: ltauxe@ucsd.edu
License: BSD-3
Keywords: geology paleomagnetism
Platform: UNKNOWN
Classifier: Development Status :: 4 - Beta
Classifier: License :: OSI Approved :: MIT License
Classifier: Programming Language :: Python :: 2
Classifier: Programming Language :: Python :: 2.6
Classifier: Programming Language :: Python :: 2.7
Classifier: Programming Language :: Python :: 3
Classifier: Programming Language :: Python :: 3.5
Classifier: Programming Language :: Python :: 3.6
Requires-Python: >=3.4
